{
    "input_file": "data/processed\\dataset_final.csv",
    "output_files": {
        "X_train": "data/processed\\X_train_preproc.csv",
        "X_test": "data/processed\\X_test_preproc.csv",
        "y_train": "data/processed\\y_train.csv",
        "y_test": "data/processed\\y_test.csv",
        "pipeline": "models\\pipeline_entrenado.joblib"
    },
    "script_used": "preprocessing_pipeline.py",
    "execution_timestamp": "2025-11-17T10:44:15.913990",
    "final_data_shape": {
        "X_train": {
            "rows": 826,
            "columns": 40
        },
        "X_test": {
            "rows": 355,
            "columns": 40
        },
        "y_train": {
            "rows": 826
        },
        "y_test": {
            "rows": 355
        }
    },
    "pipeline_summary": "Full preprocessing and feature selection pipeline.",
    "pipeline_steps": [
        "preprocessor",
        "lasso_top40"
    ],
    "final_features": [
        "num__Servicios (Kw)^2",
        "num__Frio (Kw)_movavg_3",
        "num__Servicios (Kw) KW Trafo 11",
        "num__Servicios (Kw)",
        "num__EE Servicios / Hl",
        "num__Sala Maq (Kw)",
        "num__Meta ET Linea 2",
        "num__EE Sala Maq / Hl",
        "num__diferencia_EE Servicios / Hl",
        "num__Elaboracion (Kw)_movavg_3",
        "num__ET Bodega/Hl KW Trafo 11",
        "num__ET Servicios / Hl Sala Maq (Kw)_lag3",
        "num__Linea 2 (Kw)_movavg_3",
        "num__ratio_Cocina_SalaMaq",
        "num__KW Enfluente Efl",
        "num__Sala Maq (Kw)_movavg_3 KW Trafo 11",
        "num__Efluentes (Kw)_movavg_3",
        "num__Frio (Kw) Frio (Kw)_lag3",
        "num__diferencia_EE Frio / Hl",
        "num__Sala Maq (Kw)_lag3^2",
        "num__Meta ET Planta",
        "num__Sala Maq (Kw)_lag1 ET Servicios / Hl",
        "num__Meta ET Linea 3",
        "num__ET Bodega/Hl^2",
        "num__VAPOR DE CALDERA 4 KG",
        "num__KW Trafo 9",
        "num__diferencia_Agua Planta / Hl",
        "num__Frio (Kw)_lag3 ET Servicios / Hl",
        "num__Pta Agua / Eflu (Kw)",
        "num__KW Trafo 11",
        "num__Servicios (Kw) Frio (Kw)_lag3",
        "num__Frio (Kw) Servicios (Kw)_lag3",
        "num__Frio (Kw)_lag1",
        "num__Linea 3 (Kw)_movavg_3",
        "num__Frio (Kw) KW Trafo 11",
        "num__Efluentes (Kw)",
        "num__Frio (Kw) Sala Maq (Kw)_lag3",
        "num__Frio (Kw)_movavg_3 KW Gral Planta",
        "cyc__DIA_DEL_ANIO_sin",
        "num__Totalizador Sistema Kaeser"
    ],
    "description": "Dataset procesado con OutlierReplacer, TimeSeriesInterpolatorSafe, ConstantFeatureRemover, PowerTransformer, StandardScaler, CyclicalEncoder, y TopNLasso(n=40)."
}